Metadata-Version: 1.0
Name: yaargh-dummy-argh
Version: 0.0.2
Summary: Dummy argh module that proxies yaargh
Home-page: UNKNOWN
Author: Mike Lang
Author-email: mikelang3000+yaargh@gmail.com
License: UNKNOWN
Platform: UNKNOWN
